typsht/__init__.py
typsht/cli.py
typsht/py.typed
typsht/_internal/__init__.py
typsht/_internal/checkers.py
typsht/_internal/pytest_plugin.py
typsht/_internal/runner.py
typsht/_internal/types.py
typsht-0.0.1a4.dist-info/METADATA
typsht-0.0.1a4.dist-info/WHEEL
typsht-0.0.1a4.dist-info/entry_points.txt
typsht-0.0.1a4.dist-info/RECORD
