Metadata-Version: 2.4
Name: typsht
Version: 0.0.1a4
Summary: type checker agnostic parallel type checking tool
Author-email: zzstoatzz <thrast36@gmail.com>
License-Expression: Apache-2.0
Keywords: mypy,pyre,pyright,testing,ty,type-checking
Requires-Python: >=3.10
Requires-Dist: cyclopts>=3.0.0
Requires-Dist: mypy>=1.14.0
Requires-Dist: pyre-check>=0.9.0
Requires-Dist: pyright>=1.1.0
Requires-Dist: pyyaml>=6.0.0
Requires-Dist: rich>=13.0.0
Requires-Dist: ty>=0.0.1a25
